<?xml version="1.0" encoding="UTF-8"?>
<!DOCTYPE Screen SYSTEM "https://corepunch.github.io/orca/schemas/orca.dtd">
<Screen Name="Application" Width="1280" Height="800" ClearColor="$surface" StyleSheet="Example/Styles/app.css">
	<Grid Name="Root" Rows="64px auto" class="app-shell">
		<StackView Name="NavBar" class="panel navbar">
			<StackView Name="BrandMark" class="brand-mark">
				<ImageView Name="BrandIcon" class="brand-icon" Source="Example/Icons/blocks.svg?width=22&amp;type=mask"/>
				<TextBlock Name="Brand" class="brand-text">ORCA</TextBlock>
			</StackView>
			<TextBlock Name="NavOverview" class="nav-link">Overview</TextBlock>
			<TextBlock Name="NavFeatures" class="nav-link">Features</TextBlock>
			<TextBlock Name="NavGallery" class="nav-link">Gallery</TextBlock>
			<TextBlock Name="NavDocs" class="nav-link">Docs</TextBlock>
		</StackView>
		<StackView Name="Body" class="app-body">
			<BindingExpression Target="Node.HorizontalPadding">IF(STEP(640, {Screen.Width}), Vector2(40,40), Vector2(8,8))</BindingExpression>
			<Grid Name="Hero" Columns="auto auto" class="hero">
				<StackView Name="HeroContent" class="hero-content">
					<TextBlock Name="HeadlineLine1" class="hero-title">Build stunning</TextBlock>
					<TextBlock Name="HeadlineLine2" class="hero-title-accent">UI in real-time.</TextBlock>
					<Node2D Name="HeadlineSpacer" class="headline-spacer"/>
					<TextBlock Name="SubHeadline" class="hero-subtitle">A modern UI engine for games and native apps. Compose layouts from grids, stacks, text, and images — all rendered at 60 fps.</TextBlock>
					<Node2D Name="MetricSpacer" class="metric-spacer"/>
					<Grid Name="Metrics" Columns="auto auto auto" class="grid">
						<LayerPrefabPlaceholder Name="MetricUsers" PlaceholderTemplate="Example/Prefabs/Mertic" Card.Title="2.4 M" Card.Subtitle="Active users" Card.PrimaryColor="$accent"/>
						<LayerPrefabPlaceholder Name="MetricUptime" PlaceholderTemplate="Example/Prefabs/Mertic" Card.Title="99.9 %" Card.Subtitle="Uptime SLA" Card.PrimaryColor="$accent-green"/>
						<LayerPrefabPlaceholder Name="MetricFrame" PlaceholderTemplate="Example/Prefabs/Mertic" Card.Title="1.2 ms" Card.Subtitle="Frame time" Card.PrimaryColor="$accent-blue"/>
					</Grid>
				</StackView>
				<ImageView Name="HeroImage" Source="Example/Images/people" Stretch="UniformToFill"/>
				<BindingExpression Target="Node.Visible">STEP(640, {Screen.Width})</BindingExpression>
				<BindingExpression Target="Grid.Columns">IF(STEP(640, {Screen.Width}), "auto auto", "auto")</BindingExpression>
			</Grid>
			<StackView Name="TabbedTechSection" class="section surface-section">
				<BindingExpression Target="Node.HorizontalPadding">IF(STEP(640, {Screen.Width}), Vector2(40,40), Vector2(8,8))</BindingExpression>
				<TextBlock Name="TabbedTechHeading" class="section-heading" Text="Build the UI, not the ceremony"/>
				<TextBlock Name="TabbedTechSubheading" class="section-copy"
					Text="A clean XML surface, Lua where things move, MoonScript when the app grows, and one UI that can travel across targets."/>
				<Grid Name="OrcaSignals" Columns="auto auto auto" class="grid">
					<BindingExpression Target="Grid.Columns">IF(STEP(640, {Screen.Width}), "auto auto auto", "auto auto")</BindingExpression>
					<LayerPrefabPlaceholder Name="SignalXml" PlaceholderTemplate="Example/Prefabs/SignalCard"
						Card.Icon="Example/Icons/code.svg?width=28&amp;type=mask" Card.Title="XML-first screens"
						Card.Body="Layouts stay readable." Card.PrimaryColor="$accent"/>
					<LayerPrefabPlaceholder Name="SignalLua" PlaceholderTemplate="Example/Prefabs/SignalCard"
						Card.Icon="Example/Icons/file.svg?width=28&amp;type=mask" Card.Title="Lua beside the view"
						Card.Body="Behavior stays close." Card.PrimaryColor="$accent-blue"/>
					<LayerPrefabPlaceholder Name="SignalMoon" PlaceholderTemplate="Example/Prefabs/SignalCard"
						Card.Icon="Example/Icons/moon.svg?width=28&amp;type=mask" Card.Title="MoonScript when it grows"
						Card.Body="Less noise, same runtime." Card.PrimaryColor="$text-secondary"/>
					<LayerPrefabPlaceholder Name="SignalShip" PlaceholderTemplate="Example/Prefabs/SignalCard"
						Card.Icon="Example/Icons/globe.svg?width=28&amp;type=mask" Card.Title="Desktop, mobile, web"
						Card.Body="One screen, many targets." Card.PrimaryColor="$accent-green"/>
					<LayerPrefabPlaceholder Name="SignalSpeed" PlaceholderTemplate="Example/Prefabs/SignalCard"
						Card.Icon="Example/Icons/zap.svg?width=28&amp;type=mask" Card.Title="Fast edit-run-refine"
						Card.Body="See changes immediately." Card.PrimaryColor="$accent-amber"/>
					<LayerPrefabPlaceholder Name="SignalScale" PlaceholderTemplate="Example/Prefabs/SignalCard"
						Card.Icon="Example/Icons/cpu.svg?width=28&amp;type=mask" Card.Title="Built to scale"
						Card.Body="Same UI, larger ambitions." Card.PrimaryColor="$text-muted"/>
				</Grid>
				<TabView Name="OrcaTabs" SelectedValue="xml">
					<TabBar Name="OrcaTabBar" class="panel tabbar">
						<Tab Name="XmlTab" Value="xml" class="tab">XML</Tab>
						<Tab Name="LuaTab" Value="lua" class="tab">Lua</Tab>
						<Tab Name="MoonTab" Value="moon" class="tab">MoonScript</Tab>
						<Tab Name="DeployTab" Value="deploy" class="tab">Deploy</Tab>
					</TabBar>
					<StackView Name="xml" class="tab-panel">
						<LayerPrefabPlaceholder Name="XmlPanelHeader" PlaceholderTemplate="Example/Prefabs/TabPanelHeader"
							Card.Icon="Example/Icons/grid.svg?width=26&amp;type=mask" Card.Title="XML reads like a blueprint"
							Card.PrimaryColor="$accent"/>
						<Grid Name="XmlGrid" Columns="auto auto" class="grid">
							<StackView Name="XmlCopy" class="copy-stack">
								<TextBlock Name="XmlBody" class="section-copy"
									Text="The screen stays legible at a glance, which makes it easy to scan, compare, and reshape as the design evolves."/>
								<StackView Name="XmlNotes" class="panel note-panel">
									<TextBlock Name="XmlNote1" class="note-text" Text="• Grids and stacks stay visible in the source."/>
									<TextBlock Name="XmlNote2" class="note-text" Text="• Spacing, padding, and hierarchy remain explicit."/>
									<TextBlock Name="XmlNote3" class="note-text" Text="• The shape of the screen is easy to read before it ever runs."/>
								</StackView>
							</StackView>
							<StackView Name="XmlModel" class="card stack-card model-panel">
								<TextBlock Name="XmlModelHeading" class="card-title" Text="The structure stays honest"/>
								<LayerPrefabPlaceholder Name="XmlModelLine1" class="model-indent-root" PlaceholderTemplate="Example/Prefabs/XmlModelNode"
									Card.Icon="Example/Icons/monitor.svg?width=20&amp;type=mask" Card.Title="Screen"
									Card.PrimaryColor="$accent"/>
								<LayerPrefabPlaceholder Name="XmlModelLine2" class="model-indent-child" PlaceholderTemplate="Example/Prefabs/XmlModelNode"
									Card.Icon="Example/Icons/panel-top.svg?width=20&amp;type=mask" Card.Title="TabView"
									Card.PrimaryColor="$text-secondary"/>
								<LayerPrefabPlaceholder Name="XmlModelLine3" class="model-indent-grandchild" PlaceholderTemplate="Example/Prefabs/XmlModelNode"
									Card.Icon="Example/Icons/grid.svg?width=20&amp;type=mask" Card.Title="Grid"
									Card.PrimaryColor="$text-secondary"/>
								<LayerPrefabPlaceholder Name="XmlModelLine4" class="model-indent-grandchild" PlaceholderTemplate="Example/Prefabs/XmlModelNode"
									Card.Icon="Example/Icons/layers.svg?width=20&amp;type=mask" Card.Title="StackView"
									Card.PrimaryColor="$text-secondary"/>
								<LayerPrefabPlaceholder Name="XmlModelLine5" class="model-indent-leaf" PlaceholderTemplate="Example/Prefabs/XmlModelNode"
									Card.Icon="Example/Icons/image.svg?width=20&amp;type=mask" Card.Title="ImageView"
									Card.PrimaryColor="$text-secondary"/>
								<LayerPrefabPlaceholder Name="XmlModelLine6" class="model-indent-leaf" PlaceholderTemplate="Example/Prefabs/XmlModelNode"
									Card.Icon="Example/Icons/type.svg?width=20&amp;type=mask" Card.Title="TextBlock"
									Card.PrimaryColor="$text-secondary"/>
							</StackView>
						</Grid>
					</StackView>
					<StackView Name="lua" class="tab-panel">
						<LayerPrefabPlaceholder Name="LuaPanelHeader" PlaceholderTemplate="Example/Prefabs/TabPanelHeader"
							Card.Icon="Example/Icons/code.svg?width=26&amp;type=mask" Card.Title="Lua stays close to the surface"
							Card.PrimaryColor="$accent-blue"/>
						<TextBlock Name="LuaBody" class="section-copy"
							Text="The parts that move stay beside the screen that uses them, so interaction and state feel close and easy to change."/>
						<Grid Name="LuaGrid" Columns="auto auto auto" class="grid">
							<LayerPrefabPlaceholder Name="LuaCard1" PlaceholderTemplate="Example/Prefabs/IconCard"
								Card.Icon="Example/Icons/mouse-pointer-click.svg?width=40&amp;type=mask" Card.Title="Input"
								Card.Body="Tap, click, and selection handling can sit right beside the view that needs it."
								Card.PrimaryColor="$accent" Card.IconBackground="$icon-bg-purple"/>
							<LayerPrefabPlaceholder Name="LuaCard2" PlaceholderTemplate="Example/Prefabs/IconCard"
								Card.Icon="Example/Icons/database.svg?width=40&amp;type=mask" Card.Title="State"
								Card.Body="Small state objects stay local, so the screen remains easy to reason about."
								Card.PrimaryColor="$accent-blue" Card.IconBackground="$icon-bg-blue"/>
							<LayerPrefabPlaceholder Name="LuaCard3" PlaceholderTemplate="Example/Prefabs/IconCard"
								Card.Icon="Example/Icons/link-2.svg?width=40&amp;type=mask" Card.Title="Binding"
								Card.Body="Let Lua connect the moving pieces while XML keeps the hierarchy in view."
								Card.PrimaryColor="$accent-green" Card.IconBackground="$icon-bg-green"/>
						</Grid>
					</StackView>
					<StackView Name="moon" class="tab-panel">
						<LayerPrefabPlaceholder Name="MoonPanelHeader" PlaceholderTemplate="Example/Prefabs/TabPanelHeader"
							Card.Icon="Example/Icons/moon.svg?width=26&amp;type=mask" Card.Title="MoonScript trims the noise"
							Card.PrimaryColor="$text-secondary"/>
						<Grid Name="MoonGrid" Columns="auto auto" class="grid">
							<StackView Name="MoonCopy" class="copy-stack">
								<TextBlock Name="MoonBody" class="section-copy"
									Text="MoonScript keeps larger app code compact and expressive, while still compiling to the same Lua runtime."/>
								<StackView Name="MoonNotes" class="panel note-panel">
									<TextBlock Name="MoonNote1" class="note-text" Text="• Helpful when app modules get a little larger."/>
									<TextBlock Name="MoonNote2" class="note-text" Text="• The syntax stays concise, but the runtime stays Lua."/>
									<TextBlock Name="MoonNote3" class="note-text" Text="• It pairs naturally with XML screens and Lua helpers."/>
								</StackView>
							</StackView>
							<StackView Name="MoonModel" class="card stack-card model-panel">
								<TextBlock Name="MoonModelHeading" class="card-title" Text="Same runtime, less ceremony"/>
								<TextBlock Name="MoonModelLine1" class="moon-model-line" Text="Cleaner class bodies"/>
								<TextBlock Name="MoonModelLine2" class="moon-model-line" Text="Readable app controllers"/>
								<TextBlock Name="MoonModelLine3" class="moon-model-line" Text="Plain Lua at runtime"/>
								<TextBlock Name="MoonModelLine4" class="moon-model-line" Text="Comfortable beside XML layouts"/>
							</StackView>
						</Grid>
					</StackView>
					<StackView Name="deploy" class="tab-panel">
						<LayerPrefabPlaceholder Name="DeployPanelHeader" PlaceholderTemplate="Example/Prefabs/TabPanelHeader"
							Card.Icon="Example/Icons/globe.svg?width=26&amp;type=mask" Card.Title="One UI, many targets"
							Card.PrimaryColor="$accent-green"/>
						<TextBlock Name="DeployBody" class="section-copy"
							Text="Build once, tune the spacing, and carry the same design language across desktop, mobile, and web-oriented targets."/>
						<Grid Name="DeployGrid" Columns="auto auto auto" class="grid">
							<LayerPrefabPlaceholder Name="DeployCard1" PlaceholderTemplate="Example/Prefabs/IconCard"
								Card.Icon="Example/Icons/monitor.svg?width=40&amp;type=mask" Card.Title="Desktop"
								Card.Body="Best when you want denser information, more breathing room, and precision input."
								Card.PrimaryColor="$accent" Card.IconBackground="$icon-bg-purple"/>
							<LayerPrefabPlaceholder Name="DeployCard2" PlaceholderTemplate="Example/Prefabs/IconCard"
								Card.Icon="Example/Icons/smartphone.svg?width=40&amp;type=mask" Card.Title="Mobile"
								Card.Body="Responsive spacing keeps the same interface calm and touch-friendly on smaller screens."
								Card.PrimaryColor="$accent-green" Card.IconBackground="$icon-bg-green"/>
							<LayerPrefabPlaceholder Name="DeployCard3" PlaceholderTemplate="Example/Prefabs/IconCard"
								Card.Icon="Example/Icons/globe.svg?width=40&amp;type=mask" Card.Title="Web"
								Card.Body="The same screen model can carry into browser workflows without being rewritten."
								Card.PrimaryColor="$accent-blue" Card.IconBackground="$icon-bg-blue"/>
						</Grid>
						<Grid Name="DeployImages" Columns="auto auto" class="grid">
							<LayerPrefabPlaceholder Name="DeployImage1" PlaceholderTemplate="Example/Prefabs/ImageCaptionCard"
								Card.Image="Example/Images/orca-tab-city" Card.Title="City glow"/>
							<LayerPrefabPlaceholder Name="DeployImage2" PlaceholderTemplate="Example/Prefabs/ImageCaptionCard"
								Card.Image="Example/Images/orca-tab-lights" Card.Title="Night light"/>
						</Grid>
						<StackView Name="DeployCommandLink" class="panel command-link">
							<ImageView Name="DeployCommandIcon" class="command-icon" Source="Example/Icons/monitor.svg?width=20&amp;type=mask"/>
							<StackView Name="DeployCommandCopy" class="command-copy">
								<TextBlock Name="DeployCommandLabel" class="command-label" Text="Desktop build"/>
								<TextBlock Name="DeployCommandValue" class="command-value" Text="make clean &amp;&amp; make -j8 &amp;&amp; build/bin/orca samples/Example"/>
							</StackView>
						</StackView>
					</StackView>
				</TabView>
			</StackView>
			<Grid Name="FeatureSection" Columns="auto auto auto auto" class="grid">
				<LayerPrefabPlaceholder Name="FeatureXmlCard" PlaceholderTemplate="Example/Prefabs/FeatureImageCard"
					Card.Icon="Example/Icons/layers.svg?width=40&amp;type=mask" Card.Title="XML stays readable"
					Card.Body="The layout tree is right there in the page, so structure and spacing stay easy to tune."
					Card.PrimaryColor="$accent-blue"/>
				<LayerPrefabPlaceholder Name="FeatureLuaCard" PlaceholderTemplate="Example/Prefabs/FeatureImageCard"
					Card.Icon="Example/Icons/monitor.svg?width=40&amp;type=mask" Card.Title="Lua stays close"
					Card.Body="Interactions, bindings, and state can live next to the screen that owns them."
					Card.PrimaryColor="$accent-green"/>
				<LayerPrefabPlaceholder Name="FeatureShipCard" PlaceholderTemplate="Example/Prefabs/FeatureImageCard"
					Card.Icon="Example/Icons/globe.svg?width=40&amp;type=mask" Card.Title="Ships everywhere"
					Card.Body="The same UI can move across desktop, mobile, and web-friendly targets."
					Card.PrimaryColor="$accent-amber"/>
				<LayerPrefabPlaceholder Name="FeatureSpeedCard" PlaceholderTemplate="Example/Prefabs/FeatureImageCard"
					Card.Icon="Example/Icons/zap.svg?width=40&amp;type=mask" Card.Title="Fast iteration"
					Card.Body="Edit, reload, and refine quickly without losing the overall shape of the interface."
					Card.PrimaryColor="$accent"/>
			</Grid>
			<StackView Name="GallerySection" class="section surface-section">
				<BindingExpression Target="Node.HorizontalPadding">IF(STEP(640, {Screen.Width}), Vector2(40,40), Vector2(8,8))</BindingExpression>
				<TextBlock Name="GalleryHeading" class="section-heading" Text="Gallery"/>
				<TextBlock Name="GallerySubheading" class="section-copy"
					Text="Screenshots and scenes rendered entirely by the ORCA engine."/>
				<Grid Name="GalleryGrid" Columns="auto auto" class="grid">
					<LayerPrefabPlaceholder Name="GalleryCard1" PlaceholderTemplate="Example/Prefabs/GalleryCard"
						Card.Image="Example/Images/lake" Card.Title="Lake Scene"
						Card.Subtitle="Real-time reflections and water surface rendered at 60 fps."/>
					<LayerPrefabPlaceholder Name="GalleryCard2" PlaceholderTemplate="Example/Prefabs/GalleryCard"
						Card.Image="Example/Images/peacock" Card.Title="Peacock"
						Card.Subtitle="High-fidelity texture sampling with anisotropic filtering."/>
				</Grid>
			</StackView>
			<StackView Name="WorkflowSection" class="section deep-section">
				<BindingExpression Target="Node.HorizontalPadding">IF(STEP(640, {Screen.Width}), Vector2(40,40), Vector2(8,8))</BindingExpression>
				<TextBlock Name="WorkflowHeading" class="section-heading" Text="How It Works"/>
				<TextBlock Name="WorkflowSubheading" class="section-copy"
					Text="From XML layout to a live rendered scene in four simple steps."/>
				<Grid Name="WorkflowSteps" Columns="auto auto auto auto" class="grid">
					<BindingExpression Target="Grid.Columns">IF(STEP(640, {Screen.Width}), "auto auto auto auto", "auto auto")</BindingExpression>
					<LayerPrefabPlaceholder Name="Step1" PlaceholderTemplate="Example/Prefabs/WorkflowStep"
						Card.Title="01" Card.Subtitle="Define Layout" Card.PrimaryColor="$accent"
						Card.Body="Write your screen as an XML file with familiar Grid and StackView containers."/>
					<LayerPrefabPlaceholder Name="Step2" PlaceholderTemplate="Example/Prefabs/WorkflowStep"
						Card.Title="02" Card.Subtitle="Load Assets" Card.PrimaryColor="$accent-blue"
						Card.Body="Images, fonts, and data files are streamed from packages at runtime."/>
					<LayerPrefabPlaceholder Name="Step3" PlaceholderTemplate="Example/Prefabs/WorkflowStep"
						Card.Title="03" Card.Subtitle="Script Logic" Card.PrimaryColor="$accent-green"
						Card.Body="Attach Lua scripts to any component for interactivity and data binding."/>
					<LayerPrefabPlaceholder Name="Step4" PlaceholderTemplate="Example/Prefabs/WorkflowStep"
						Card.Title="04" Card.Subtitle="Ship" Card.PrimaryColor="$accent-amber"
						Card.Body="Deploy to desktop, mobile, or WebGL with a single build command."/>
				</Grid>
			</StackView>
			<StackView Name="TestimonialsSection" class="section surface-section">
				<BindingExpression Target="Node.HorizontalPadding">IF(STEP(640, {Screen.Width}), Vector2(40,40), Vector2(8,8))</BindingExpression>
				<TextBlock Name="TestimonialsHeading" class="section-heading" Text="What Developers Say"/>
				<Grid Name="TestimonialsGrid" Columns="auto auto auto" class="grid">
					<LayerPrefabPlaceholder Name="Quote1" PlaceholderTemplate="Example/Prefabs/Quote"
						Card.PrimaryColor="$accent" Card.Title="— Alex R." Card.Subtitle="Lead Engineer"
						Card.Body="ORCA lets us ship native-quality UI on every platform from a single XML source. It changed how we build products."/>
					<LayerPrefabPlaceholder Name="Quote2" PlaceholderTemplate="Example/Prefabs/Quote"
						Card.PrimaryColor="$accent-green" Card.Title="— Sam T." Card.Subtitle="UI Architect"
						Card.Body="The declarative layout system is a joy to work with. Our designers write XML and developers hook up the logic — perfect split."/>
					<LayerPrefabPlaceholder Name="Quote3" PlaceholderTemplate="Example/Prefabs/Quote"
						Card.PrimaryColor="$accent-blue" Card.Title="— Jordan M." Card.Subtitle="Game Developer"
						Card.Body="Sub-millisecond frame times even on mid-range hardware. We ditched our old HTML renderer the day we tried ORCA."/>
				</Grid>
			</StackView>
			<StackView Name="CtaSection" class="section panel cta-section">
				<BindingExpression Target="Node.HorizontalPadding">IF(STEP(640, {Screen.Width}), Vector2(60,60), Vector2(16,16))</BindingExpression>
				<TextBlock Name="CtaHeading" class="cta-heading" Text="Ready to build something great?"/>
				<TextBlock Name="CtaBody" class="cta-body"
					Text="Download ORCA, open a sample project, and have your first screen running in minutes."/>
				<StackView Name="CtaButtons" class="cta-button-row">
					<TextBlock Name="CtaButtonPrimary" class="button cta-button primary-button" Text="Get Started"
						LeftButtonUp="{Screen.ShowModal Path=Example/Screens/GetStartedPopup}"/>
					<TextBlock Name="CtaButtonSecondary" class="button cta-button secondary-button" Text="Learn more"/>
				</StackView>
			</StackView>
		</StackView>
	</Grid>
</Screen>
